opensarlab_doc_link/__init__.py
opensarlab_doc_link/_version.py
opensarlab_doc_link/labextension/build_log.json
opensarlab_doc_link/labextension/package.json
opensarlab_doc_link/labextension/static/lib_index_js.daaed9aabfd76f9cc917.js
opensarlab_doc_link/labextension/static/lib_index_js.daaed9aabfd76f9cc917.js.map
opensarlab_doc_link/labextension/static/remoteEntry.f8c7bb03277ea31d379f.js
opensarlab_doc_link/labextension/static/remoteEntry.f8c7bb03277ea31d379f.js.map
opensarlab_doc_link/labextension/static/style.js
opensarlab_doc_link/labextension/static/style_index_js.ed77571c12bc466dc027.js
opensarlab_doc_link/labextension/static/style_index_js.ed77571c12bc466dc027.js.map
opensarlab_doc_link/labextension/static/vendors-node_modules_css-loader_dist_runtime_api_js-node_modules_css-loader_dist_runtime_cssW-72eba1.eec3f5314b643e4b3c21.js
opensarlab_doc_link/labextension/static/vendors-node_modules_css-loader_dist_runtime_api_js-node_modules_css-loader_dist_runtime_cssW-72eba1.eec3f5314b643e4b3c21.js.map
opensarlab_doc_link/labextension/static/vendors-node_modules_jupyterlab-topbar_lib_index_js.5ebae736da3eb0da75f1.js
opensarlab_doc_link/labextension/static/vendors-node_modules_jupyterlab-topbar_lib_index_js.5ebae736da3eb0da75f1.js.map
opensarlab_doc_link-0.1.0.data/data/share/jupyter/labextensions/opensarlab-doc-link/build_log.json
opensarlab_doc_link-0.1.0.data/data/share/jupyter/labextensions/opensarlab-doc-link/install.json
opensarlab_doc_link-0.1.0.data/data/share/jupyter/labextensions/opensarlab-doc-link/package.json
opensarlab_doc_link-0.1.0.data/data/share/jupyter/labextensions/opensarlab-doc-link/static/lib_index_js.daaed9aabfd76f9cc917.js
opensarlab_doc_link-0.1.0.data/data/share/jupyter/labextensions/opensarlab-doc-link/static/lib_index_js.daaed9aabfd76f9cc917.js.map
opensarlab_doc_link-0.1.0.data/data/share/jupyter/labextensions/opensarlab-doc-link/static/remoteEntry.f8c7bb03277ea31d379f.js
opensarlab_doc_link-0.1.0.dist-info/LICENSE
opensarlab_doc_link-0.1.0.dist-info/METADATA
opensarlab_doc_link-0.1.0.dist-info/WHEEL
opensarlab_doc_link-0.1.0.dist-info/top_level.txt
opensarlab_doc_link-0.1.0.dist-info/RECORD
